odoo/addons/mrp_multi_level_estimate/README.rst
odoo/addons/mrp_multi_level_estimate/__init__.py
odoo/addons/mrp_multi_level_estimate/__manifest__.py
odoo/addons/mrp_multi_level_estimate/i18n/es.po
odoo/addons/mrp_multi_level_estimate/i18n/it.po
odoo/addons/mrp_multi_level_estimate/i18n/mrp_multi_level_estimate.pot
odoo/addons/mrp_multi_level_estimate/models/__init__.py
odoo/addons/mrp_multi_level_estimate/models/mrp_area.py
odoo/addons/mrp_multi_level_estimate/models/product_mrp_area.py
odoo/addons/mrp_multi_level_estimate/readme/CONFIGURE.rst
odoo/addons/mrp_multi_level_estimate/readme/CONTRIBUTORS.rst
odoo/addons/mrp_multi_level_estimate/readme/DESCRIPTION.rst
odoo/addons/mrp_multi_level_estimate/static/description/icon.png
odoo/addons/mrp_multi_level_estimate/static/description/index.html
odoo/addons/mrp_multi_level_estimate/tests/__init__.py
odoo/addons/mrp_multi_level_estimate/tests/test_mrp_multi_level_estimate.py
odoo/addons/mrp_multi_level_estimate/views/mrp_area_views.xml
odoo/addons/mrp_multi_level_estimate/views/product_mrp_area_views.xml
odoo/addons/mrp_multi_level_estimate/wizards/__init__.py
odoo/addons/mrp_multi_level_estimate/wizards/mrp_multi_level.py
odoo14_addon_mrp_multi_level_estimate-14.0.1.1.2.dist-info/METADATA
odoo14_addon_mrp_multi_level_estimate-14.0.1.1.2.dist-info/WHEEL
odoo14_addon_mrp_multi_level_estimate-14.0.1.1.2.dist-info/top_level.txt
odoo14_addon_mrp_multi_level_estimate-14.0.1.1.2.dist-info/RECORD
